<?xml version="1.0" encoding="utf-8" ?><dwsync><file name="init.php" server="westoforange.com:27912//var/www/" local="3592918466" remote="16477820353" /><file name="side_nav.php" server="westoforange.com:27912//var/www/" local="3592918454" remote="16477820342" /><file name="database.php" server="westoforange.com:27912//var/www/" local="3588937514" remote="16473839402" /><file name="top_nav.php" server="westoforange.com:27912//var/www/" local="3588763718" remote="16473665606" /><file name="footer.php" server="westoforange.com:27912//var/www/" local="3588691529" remote="16473593417" /><file name="categories.php" server="westoforange.com:27912//var/www/" local="3588795061" remote="16473696949" /><file name="tags.php" server="westoforange.com:27912//var/www/" local="3588778468" remote="16473680356" /><file name="rewrite.php" server="westoforange.com:27912//var/www/" local="3588768630" remote="16473670518" /><file name="functions.php" server="westoforange.com:27912//var/www/" local="3590084291" remote="16474986179" /></dwsync>